graphql_client/__init__.py
py_graphql_client-0.1.2.dist-info/LICENSE
py_graphql_client-0.1.2.dist-info/METADATA
py_graphql_client-0.1.2.dist-info/WHEEL
py_graphql_client-0.1.2.dist-info/top_level.txt
py_graphql_client-0.1.2.dist-info/RECORD
