Metadata-Version: 2.1
Name: py-graphql-client
Version: 0.1.2
Summary: A dead-simple GraphQL client that supports subscriptions over websockets
Home-page: https://github.com/ecthiender/py-graphql-client
Author: Anon Ray
Author-email: rayanon004@gmail.com
License: BSD3
Keywords: graphql,websocket,subscriptions,graphql-client
Classifier: Development Status :: 3 - Alpha
Classifier: Intended Audience :: Developers
Classifier: License :: OSI Approved :: BSD License
Classifier: Natural Language :: English
Classifier: Programming Language :: Python :: 3
Classifier: Programming Language :: Python :: 3.8
Classifier: Environment :: Console
Classifier: Environment :: Web Environment
Classifier: Environment :: Other Environment
Classifier: Topic :: Internet :: WWW/HTTP
Classifier: Topic :: Software Development :: Libraries
Requires-Python: >=3.4
License-File: LICENSE
Requires-Dist: websocket-client (==0.54.0)
